pysettings_yaml/__init__.py
pysettings_yaml/loader.py
pysettings_yaml/providers/__init__.py
pysettings_yaml/providers/decouple.py
pysettings_yaml/providers/direct.py
pysettings_yaml/providers/interfaces.py
pysettings_yaml/utils.py
pysettings_yaml-0.1.2.dist-info/WHEEL
pysettings_yaml-0.1.2.dist-info/METADATA
pysettings_yaml-0.1.2.dist-info/RECORD
