Metadata-Version: 2.1
Name: pysettings-yaml
Version: 0.1.2
Summary: Settings library for human beings
Home-page: https://github.com/Rydra/pysettings-yaml
Keywords: settings
Author: David
Author-email: davigetto@gmail.com
Requires-Python: >=3.8,<4.0
Classifier: Programming Language :: Python :: 3
Classifier: Programming Language :: Python :: 3.10
Classifier: Programming Language :: Python :: 3.8
Classifier: Programming Language :: Python :: 3.9
Requires-Dist: PyYAML (>=6.0,<7.0)
Requires-Dist: deepmerge (>=1.1.0,<2.0.0)
Requires-Dist: funcy (>=1.17,<2.0)
Requires-Dist: pydantic (>=1.10.2,<2.0.0)
Requires-Dist: python-decouple (>=3.6,<4.0)
Requires-Dist: split-settings (>=1.0.0,<2.0.0)
Project-URL: Repository, https://github.com/Rydra/pysettings-yaml
